iamporter/__init__.py
iamporter/api.py
iamporter/base.py
iamporter/client.py
iamporter/consts.py
iamporter/errors.py
iamporter-0.2.3.dist-info/LICENSE
iamporter-0.2.3.dist-info/METADATA
iamporter-0.2.3.dist-info/WHEEL
iamporter-0.2.3.dist-info/top_level.txt
iamporter-0.2.3.dist-info/RECORD
