Metadata-Version: 2.1
Name: iamporter
Version: 0.2.3
Summary: An I'mport REST API Client for Human
Home-page: https://github.com/kde713/iamporter-python
Author: kde713
Author-email: kde713@gmail.com
License: MIT
Keywords: iamport,import,payment,iamporter
Platform: UNKNOWN
Classifier: Environment :: Web Environment
Classifier: Intended Audience :: Developers
Classifier: License :: OSI Approved :: MIT License
Classifier: Operating System :: OS Independent
Classifier: Topic :: Software Development :: Libraries :: Python Modules
Classifier: Programming Language :: Python :: 3
Classifier: Programming Language :: Python :: 3.4
Classifier: Programming Language :: Python :: 3.5
Classifier: Programming Language :: Python :: 3.6
Requires-Python: >=3
Requires-Dist: requests (~=2.21.0)
